networking_zte/__init__.py
networking_zte/common/__init__.py
networking_zte/common/servermanager.py
networking_zte/fwaas/__init__.py
networking_zte/fwaas/zenic_firewall_pool.py
networking_zte/fwaas/zenic_fwaas_plugin.py
networking_zte/l3/__init__.py
networking_zte/l3/all_l3_agents_scheduler.py
networking_zte/l3/zenic_agent.py
networking_zte/lbaas/__init__.py
networking_zte/ml2/__init__.py
networking_zte/ml2/driver_api.py
networking_zte/ml2/driver_context.py
networking_zte/ml2/ml2_neutron_driver.py
networking_zte/ml2/sync_filter.py
networking_zte/ml2/common/__init__.py
networking_zte/ml2/common/rest/__init__.py
networking_zte/ml2/common/rest/ml2_zenic/__init__.py
networking_zte/ml2/common/rest/ml2_zenic/config.py
networking_zte/ml2/common/rest/ml2_zenic/mech_zenic_l2.py
networking_zte/ml2/common/rest/ml2_zenic/ml2_zenic_restconf.py
networking_zte/qos/__init__.py
networking_zte/qos/zenic_qos_plugin.py
networking_zte/qos/zenic_qos_pool.py
networking_zte/tests/__init__.py
networking_zte/tests/base.py
networking_zte/tests/test_networking_zte.py
networking_zte/utils/__init__.py
networking_zte/utils/cmcc_util.py
usr/bin/neutron-zenic-agent
usr/lib/systemd/system/neutron-zenic-agent.service
networking_zte-1.0.0.dist-info/AUTHORS
networking_zte-1.0.0.dist-info/LICENSE
networking_zte-1.0.0.dist-info/METADATA
networking_zte-1.0.0.dist-info/WHEEL
networking_zte-1.0.0.dist-info/entry_points.txt
networking_zte-1.0.0.dist-info/pbr.json
networking_zte-1.0.0.dist-info/top_level.txt
networking_zte-1.0.0.dist-info/RECORD
